transmission_lever/__init__.py
transmission_lever/tlever.json
transmission_lever/tlever.py
transmission_lever/community/__init__.py
transmission_lever/core/__init__.py
transmission_lever/core/client.py
transmission_lever/core/config.py
transmission_lever/core/label.py
transmission_lever/core/torrent.py
transmission_lever/extra/__init__.py
transmission_lever/extra/category.py
transmission_lever/extra/clog.py
transmission_lever/extra/tag.py
transmission_lever/extra/tier.py
transmission_lever/extra/tui.py
transmission_lever-0.1.1.dist-info/METADATA
transmission_lever-0.1.1.dist-info/WHEEL
transmission_lever-0.1.1.dist-info/entry_points.txt
transmission_lever-0.1.1.dist-info/licenses/LICENSE
transmission_lever-0.1.1.dist-info/RECORD
