Metadata-Version: 2.3
Name: transmission-lever
Version: 0.1.1
Summary:  Small program that simplifies common chores on multiple torrents (currently only supports Transmission).
Project-URL: Homepage, https://github.com/tvillega/transmission-lever
Project-URL: Issues, https://github.com/tvillega/transmission-lever
Author-email: Tom Villegas <tvillega@dcc.uchile.cl>
Keywords: manage,seed,torrent,transmission
Classifier: License :: OSI Approved :: GNU Affero General Public License v3 or later (AGPLv3+)
Classifier: Operating System :: OS Independent
Classifier: Programming Language :: Python :: 3
Requires-Python: >=3.12
Requires-Dist: transmission-rpc
